adiftools/__init__.py
adiftools/adifgraph.py
adiftools/adiftools.py
adiftools/callsign.py
adiftools/gridlocator.py
adiftools/errors/__init__.py
adiftools-0.1.10.dist-info/licenses/LICENSE
adiftools-0.1.10.dist-info/METADATA
adiftools-0.1.10.dist-info/WHEEL
adiftools-0.1.10.dist-info/top_level.txt
adiftools-0.1.10.dist-info/RECORD
