Metadata-Version: 2.4
Name: adiftools
Version: 0.1.10
Summary: ADIF file utilities
Home-page: https://github.com/JS2IIU-MH/adiftools-dev
Download-URL: https://github.com/JS2IIU-MH/adiftools-dev
Author: JS2IIU
Author-email: info@js2iiu.com
Maintainer: JS2IIU
Maintainer-email: info@js2iiu.com
License: MIT
Keywords: adif
Classifier: Programming Language :: Python :: 3.11
Classifier: Programming Language :: Python :: 3.12
Classifier: Programming Language :: Python :: 3.13
Classifier: Intended Audience :: Developers
License-File: LICENSE
Requires-Dist: numpy
Requires-Dist: pandas
Requires-Dist: matplotlib
Requires-Dist: python-dateutil
Requires-Dist: pytz
Requires-Dist: six
Requires-Dist: tzdata
Requires-Dist: geographiclib
Requires-Dist: iniconfig
Requires-Dist: pluggy
Dynamic: author
Dynamic: author-email
Dynamic: description
Dynamic: description-content-type
Dynamic: download-url
Dynamic: home-page
Dynamic: keywords
Dynamic: license
Dynamic: license-file
Dynamic: maintainer
Dynamic: maintainer-email
Dynamic: requires-dist
Dynamic: summary
